CONTRIBUTORS
examples/log.py
examples/pull.py
examples/thingspeak_cpu_loop.py
thingspeak/__init__.py
thingspeak/cmdline.py
thingspeak-1.0.0.dist-info/entry_points.txt
thingspeak-1.0.0.dist-info/LICENSE
thingspeak-1.0.0.dist-info/WHEEL
thingspeak-1.0.0.dist-info/METADATA
thingspeak-1.0.0.dist-info/RECORD
